{
  "departamentos": [
    {
      "id": 1,
      "nombre": "Santander"
    }
  ],
  "ciudades": [
    {
      "id": 1,
      "departamentoId": 1,
      "nombre": "Bucaramanga"
    },
    {
      "nombre": "123",
      "departamentoID": 1,
      "id": 2
    },
    {
      "nombre": "1233",
      "departamentoID": 1,
      "id": 3
    },
    {
      "nombre": "1111",
      "departamentoID": 1,
      "id": 4
    },
    {
      "nombre": "Bucaramangas",
      "departamentoID": 1,
      "id": 5
    }
  ],
  "inmuebles": [
    {
      "id": 1,
      "ciudadId": 1,
      "precio": "750000",
      "habitaciones": "3",
      "banos": "2",
      "metros": "60",
      "direccion": "CRA 20 # 28-28 Antonio Santos",
      "departamentoId": "1"
    },
    {
      "id": 2,
      "ciudadId": 1,
      "precio": "900000",
      "habitaciones": "3",
      "banos": "2",
      "metros": "60",
      "direccion": "Blvd. Ac. 234",
      "departamentoId": "1"
    }
  ]
}